{
  "data": {
    "article": {},
    "attachments": {},
    "author_id": "2055263152238198784",
    "conversation_id": "2063692083555369311",
    "created_at": "2026-06-08T01:17:34.000Z",
    "edit_controls": {
      "editable_until": "2026-06-08T02:17:34.000Z",
      "edits_remaining": 5,
      "is_edit_eligible": false
    },
    "edit_history_tweet_ids": [
      "2063792519008452940"
    ],
    "entities": {
      "mentions": [
        {
          "end": 12,
          "id": "1925545097967673346",
          "start": 0,
          "username": "snxkdh55773"
        }
      ]
    },
    "geo": {},
    "id": "2063792519008452940",
    "in_reply_to_user_id": "1925545097967673346",
    "lang": "und",
    "note_tweet": {
      "entities": {}
    },
    "possibly_sensitive": false,
    "public_metrics": {
      "bookmark_count": 0,
      "impression_count": 0,
      "like_count": 0,
      "quote_count": 0,
      "reply_count": 0,
      "retweet_count": 0
    },
    "referenced_tweets": [
      {
        "id": "2063692083555369311",
        "type": "replied_to"
      }
    ],
    "reply_settings": "everyone",
    "text": "@snxkdh55773 2！"
  },
  "includes": {
    "media": [
      {
        "height": 1200,
        "media_key": "3_2063692074927734784",
        "public_metrics": {},
        "type": "photo",
        "url": "https://pbs.twimg.com/media/HKO1AhvbQAAXYpS.jpg",
        "width": 900
      },
      {
        "height": 1200,
        "media_key": "3_2063692074957012992",
        "public_metrics": {},
        "type": "photo",
        "url": "https://pbs.twimg.com/media/HKO1Ah2aAAAgFSZ.jpg",
        "width": 900
      }
    ],
    "tweets": [
      {
        "article": {},
        "attachments": {},
        "author_id": "2055263152238198784",
        "conversation_id": "2063692083555369311",
        "created_at": "2026-06-08T01:17:34.000Z",
        "edit_controls": {
          "editable_until": "2026-06-08T02:17:34.000Z",
          "edits_remaining": 5,
          "is_edit_eligible": false
        },
        "edit_history_tweet_ids": [
          "2063792519008452940"
        ],
        "entities": {
          "mentions": [
            {
              "end": 12,
              "id": "1925545097967673346",
              "start": 0,
              "username": "snxkdh55773"
            }
          ]
        },
        "geo": {},
        "id": "2063792519008452940",
        "in_reply_to_user_id": "1925545097967673346",
        "lang": "und",
        "note_tweet": {
          "entities": {}
        },
        "possibly_sensitive": false,
        "public_metrics": {
          "bookmark_count": 0,
          "impression_count": 0,
          "like_count": 0,
          "quote_count": 0,
          "reply_count": 0,
          "retweet_count": 0
        },
        "referenced_tweets": [
          {
            "id": "2063692083555369311",
            "type": "replied_to"
          }
        ],
        "reply_settings": "everyone",
        "text": "@snxkdh55773 2！"
      },
      {
        "article": {},
        "attachments": {
          "media_keys": [
            "3_2063692074927734784",
            "3_2063692074957012992"
          ]
        },
        "author_id": "1925545097967673346",
        "conversation_id": "2063692083555369311",
        "created_at": "2026-06-07T18:38:28.000Z",
        "edit_controls": {
          "editable_until": "2026-06-07T19:38:28.000Z",
          "edits_remaining": 5,
          "is_edit_eligible": true
        },
        "edit_history_tweet_ids": [
          "2063692083555369311"
        ],
        "entities": {
          "urls": [
            {
              "display_url": "pic.x.com/4WGA3OTgHt",
              "end": 29,
              "expanded_url": "https://x.com/snxkdh55773/status/2063692083555369311/photo/1",
              "media_key": "3_2063692074927734784",
              "start": 6,
              "url": "https://t.co/4WGA3OTgHt"
            },
            {
              "display_url": "pic.x.com/4WGA3OTgHt",
              "end": 29,
              "expanded_url": "https://x.com/snxkdh55773/status/2063692083555369311/photo/1",
              "media_key": "3_2063692074957012992",
              "start": 6,
              "url": "https://t.co/4WGA3OTgHt"
            }
          ]
        },
        "geo": {},
        "id": "2063692083555369311",
        "lang": "zh",
        "note_tweet": {
          "entities": {}
        },
        "possibly_sensitive": false,
        "public_metrics": {
          "bookmark_count": 0,
          "impression_count": 30,
          "like_count": 0,
          "quote_count": 0,
          "reply_count": 0,
          "retweet_count": 0
        },
        "reply_settings": "everyone",
        "text": "哪个好看呢 https://t.co/4WGA3OTgHt"
      }
    ],
    "users": [
      {
        "created_at": "2026-05-15T12:25:25.000Z",
        "description": "保卫胡言乱语",
        "id": "2055263152238198784",
        "name": "rei",
        "profile_image_url": "https://pbs.twimg.com/profile_images/2061638515864346625/3yEXkh-c_normal.jpg",
        "protected": false,
        "public_metrics": {
          "followers_count": 204,
          "following_count": 372,
          "like_count": 3057,
          "listed_count": 0,
          "media_count": 30,
          "tweet_count": 518
        },
        "username": "Reiau9e",
        "verified": false
      },
      {
        "created_at": "2025-05-22T13:31:52.000Z",
        "description": "4/1都行 sw 性别女 可以叫我拆拆 支持投喂\n私信欢迎 没礼貌的不要来、、\n聊天52r 想看我的日常88r\n比我漂亮的和互关免费加^ω^",
        "id": "1925545097967673346",
        "location": "天堂、！",
        "name": "很好吃",
        "profile_image_url": "https://pbs.twimg.com/profile_images/1936112004462485505/DhRO4UHN_normal.jpg",
        "protected": false,
        "public_metrics": {
          "followers_count": 295,
          "following_count": 80,
          "like_count": 1183,
          "listed_count": 1,
          "media_count": 86,
          "tweet_count": 373
        },
        "username": "snxkdh55773",
        "verified": false
      }
    ]
  }
}