{
  "data": {
    "article": {},
    "attachments": {},
    "author_id": "2055263152238198784",
    "conversation_id": "2069705362702541164",
    "created_at": "2026-06-24T13:45:46.000Z",
    "edit_controls": {
      "editable_until": "2026-06-24T14:45:46.000Z",
      "edits_remaining": 5,
      "is_edit_eligible": false
    },
    "edit_history_tweet_ids": [
      "2069779014559146388"
    ],
    "entities": {
      "mentions": [
        {
          "end": 10,
          "id": "1516328938582204421",
          "start": 0,
          "username": "yukaoxia_"
        }
      ]
    },
    "geo": {},
    "id": "2069779014559146388",
    "in_reply_to_user_id": "1516328938582204421",
    "lang": "zh",
    "note_tweet": {
      "entities": {}
    },
    "possibly_sensitive": false,
    "public_metrics": {
      "bookmark_count": 0,
      "impression_count": 0,
      "like_count": 0,
      "quote_count": 0,
      "reply_count": 0,
      "retweet_count": 0
    },
    "referenced_tweets": [
      {
        "id": "2069705362702541164",
        "type": "replied_to"
      }
    ],
    "reply_settings": "everyone",
    "text": "@yukaoxia_ 下次我也装人机阴阳人"
  },
  "includes": {
    "media": [
      {
        "height": 2048,
        "media_key": "3_2069705344104734720",
        "public_metrics": {},
        "type": "photo",
        "url": "https://pbs.twimg.com/media/HLkSC3EXIAAKDms.jpg",
        "width": 942
      }
    ],
    "tweets": [
      {
        "article": {},
        "attachments": {},
        "author_id": "2055263152238198784",
        "conversation_id": "2069705362702541164",
        "created_at": "2026-06-24T13:45:46.000Z",
        "edit_controls": {
          "editable_until": "2026-06-24T14:45:46.000Z",
          "edits_remaining": 5,
          "is_edit_eligible": false
        },
        "edit_history_tweet_ids": [
          "2069779014559146388"
        ],
        "entities": {
          "mentions": [
            {
              "end": 10,
              "id": "1516328938582204421",
              "start": 0,
              "username": "yukaoxia_"
            }
          ]
        },
        "geo": {},
        "id": "2069779014559146388",
        "in_reply_to_user_id": "1516328938582204421",
        "lang": "zh",
        "note_tweet": {
          "entities": {}
        },
        "possibly_sensitive": false,
        "public_metrics": {
          "bookmark_count": 0,
          "impression_count": 0,
          "like_count": 0,
          "quote_count": 0,
          "reply_count": 0,
          "retweet_count": 0
        },
        "referenced_tweets": [
          {
            "id": "2069705362702541164",
            "type": "replied_to"
          }
        ],
        "reply_settings": "everyone",
        "text": "@yukaoxia_ 下次我也装人机阴阳人"
      },
      {
        "article": {},
        "attachments": {
          "media_keys": [
            "3_2069705344104734720"
          ]
        },
        "author_id": "1516328938582204421",
        "conversation_id": "2069705362702541164",
        "created_at": "2026-06-24T08:53:06.000Z",
        "edit_controls": {
          "editable_until": "2026-06-24T09:53:06.000Z",
          "edits_remaining": 5,
          "is_edit_eligible": false
        },
        "edit_history_tweet_ids": [
          "2069705362702541164"
        ],
        "entities": {
          "urls": [
            {
              "display_url": "pic.x.com/SQpgrEXOFv",
              "end": 49,
              "expanded_url": "https://x.com/yukaoxia_/status/2069705362702541164/photo/1",
              "media_key": "3_2069705344104734720",
              "start": 26,
              "url": "https://t.co/SQpgrEXOFv"
            }
          ]
        },
        "geo": {},
        "id": "2069705362702541164",
        "lang": "zh",
        "note_tweet": {
          "entities": {}
        },
        "possibly_sensitive": false,
        "public_metrics": {
          "bookmark_count": 0,
          "impression_count": 1205,
          "like_count": 23,
          "quote_count": 0,
          "reply_count": 9,
          "retweet_count": 0
        },
        "reply_settings": "everyone",
        "text": "这个人机在我的美食图片里发个💩混在里面是啥意思。。 https://t.co/SQpgrEXOFv"
      }
    ],
    "users": [
      {
        "created_at": "2026-05-15T12:25:25.000Z",
        "description": "保卫胡言乱语",
        "id": "2055263152238198784",
        "name": "rei",
        "profile_image_url": "https://pbs.twimg.com/profile_images/2061638515864346625/3yEXkh-c_normal.jpg",
        "protected": false,
        "public_metrics": {
          "followers_count": 557,
          "following_count": 612,
          "like_count": 6078,
          "listed_count": 0,
          "media_count": 37,
          "tweet_count": 1124
        },
        "url": "",
        "username": "Reiau9e",
        "verified": false
      },
      {
        "created_at": "2022-04-19T08:12:55.000Z",
        "description": "一个占有欲很强的人",
        "id": "1516328938582204421",
        "name": "obeyuppy",
        "pinned_tweet_id": "2054922298411360271",
        "profile_image_url": "https://pbs.twimg.com/profile_images/2041508699249008640/w4E_tYGQ_normal.jpg",
        "protected": false,
        "public_metrics": {
          "followers_count": 1516,
          "following_count": 0,
          "like_count": 1129,
          "listed_count": 1,
          "media_count": 79,
          "tweet_count": 804
        },
        "url": "",
        "username": "yukaoxia_",
        "verified": true
      }
    ]
  }
}