{
  "data": {
    "article": {},
    "attachments": {},
    "author_id": "2055263152238198784",
    "conversation_id": "2071489020178137315",
    "created_at": "2026-06-30T15:10:00.000Z",
    "edit_controls": {
      "editable_until": "2026-06-30T16:10:00.000Z",
      "edits_remaining": 5,
      "is_edit_eligible": false
    },
    "edit_history_tweet_ids": [
      "2071974541044412656"
    ],
    "entities": {
      "mentions": [
        {
          "end": 11,
          "id": "1988187586339467264",
          "start": 0,
          "username": "Air_Yukiha"
        }
      ]
    },
    "geo": {},
    "id": "2071974541044412656",
    "in_reply_to_user_id": "1988187586339467264",
    "lang": "qme",
    "note_tweet": {
      "entities": {}
    },
    "possibly_sensitive": false,
    "public_metrics": {
      "bookmark_count": 0,
      "impression_count": 0,
      "like_count": 0,
      "quote_count": 0,
      "reply_count": 0,
      "retweet_count": 0
    },
    "referenced_tweets": [
      {
        "id": "2071969735688728613",
        "type": "replied_to"
      }
    ],
    "reply_settings": "everyone",
    "text": "@Air_Yukiha 😽😽😽😽😽"
  },
  "includes": {
    "tweets": [
      {
        "article": {},
        "attachments": {},
        "author_id": "2055263152238198784",
        "conversation_id": "2071489020178137315",
        "created_at": "2026-06-30T15:10:00.000Z",
        "edit_controls": {
          "editable_until": "2026-06-30T16:10:00.000Z",
          "edits_remaining": 5,
          "is_edit_eligible": false
        },
        "edit_history_tweet_ids": [
          "2071974541044412656"
        ],
        "entities": {
          "mentions": [
            {
              "end": 11,
              "id": "1988187586339467264",
              "start": 0,
              "username": "Air_Yukiha"
            }
          ]
        },
        "geo": {},
        "id": "2071974541044412656",
        "in_reply_to_user_id": "1988187586339467264",
        "lang": "qme",
        "note_tweet": {
          "entities": {}
        },
        "possibly_sensitive": false,
        "public_metrics": {
          "bookmark_count": 0,
          "impression_count": 0,
          "like_count": 0,
          "quote_count": 0,
          "reply_count": 0,
          "retweet_count": 0
        },
        "referenced_tweets": [
          {
            "id": "2071969735688728613",
            "type": "replied_to"
          }
        ],
        "reply_settings": "everyone",
        "text": "@Air_Yukiha 😽😽😽😽😽"
      },
      {
        "article": {},
        "attachments": {},
        "author_id": "1988187586339467264",
        "conversation_id": "2071489020178137315",
        "created_at": "2026-06-30T14:50:54.000Z",
        "edit_controls": {
          "editable_until": "2026-06-30T15:50:54.000Z",
          "edits_remaining": 5,
          "is_edit_eligible": false
        },
        "edit_history_tweet_ids": [
          "2071969735688728613"
        ],
        "entities": {
          "mentions": [
            {
              "end": 8,
              "id": "2055263152238198784",
              "start": 0,
              "username": "Reiau9e"
            }
          ]
        },
        "geo": {},
        "id": "2071969735688728613",
        "in_reply_to_user_id": "2055263152238198784",
        "lang": "zh",
        "note_tweet": {
          "entities": {}
        },
        "possibly_sensitive": false,
        "public_metrics": {
          "bookmark_count": 0,
          "impression_count": 17,
          "like_count": 1,
          "quote_count": 0,
          "reply_count": 2,
          "retweet_count": 0
        },
        "referenced_tweets": [
          {
            "id": "2071489020178137315",
            "type": "replied_to"
          }
        ],
        "reply_settings": "everyone",
        "text": "@Reiau9e 好像朦朦胧胧中看到爱人抱着自己🥹🥺感觉好适合做壁纸头像呀呀呀"
      }
    ],
    "users": [
      {
        "created_at": "2026-05-15T12:25:25.000Z",
        "description": "保卫胡言乱语",
        "id": "2055263152238198784",
        "name": "rei",
        "profile_image_url": "https://pbs.twimg.com/profile_images/2061638515864346625/3yEXkh-c_normal.jpg",
        "protected": false,
        "public_metrics": {
          "followers_count": 698,
          "following_count": 697,
          "like_count": 7007,
          "listed_count": 1,
          "media_count": 37,
          "tweet_count": 1395
        },
        "url": "",
        "username": "Reiau9e",
        "verified": false
      },
      {
        "created_at": "2025-11-11T10:10:43.000Z",
        "description": "全く可愛くない！\n一個普普通通的溫良小女孩=lvl=\n唯一教主@Numiouoo\n小惠老婆@huihui_mikumi",
        "entities": {
          "description": {
            "mentions": [
              {
                "end": 40,
                "start": 31,
                "username": "Numiouoo"
              },
              {
                "end": 59,
                "start": 45,
                "username": "huihui_mikumi"
              }
            ]
          }
        },
        "id": "1988187586339467264",
        "location": "Japan",
        "name": "翼",
        "pinned_tweet_id": "2062030452031119866",
        "profile_image_url": "https://pbs.twimg.com/profile_images/1988835836738375680/Y-Dta9uI_normal.jpg",
        "protected": false,
        "public_metrics": {
          "followers_count": 756,
          "following_count": 434,
          "like_count": 1956,
          "listed_count": 0,
          "media_count": 62,
          "tweet_count": 942
        },
        "url": "",
        "username": "Air_Yukiha",
        "verified": false
      }
    ]
  }
}